mmplayer_mcp_server-0.1.0.dist-info/licenses/LICENSE
voice/main.py
mmplayer_mcp_server-0.1.0.dist-info/METADATA
mmplayer_mcp_server-0.1.0.dist-info/WHEEL
mmplayer_mcp_server-0.1.0.dist-info/entry_points.txt
mmplayer_mcp_server-0.1.0.dist-info/top_level.txt
mmplayer_mcp_server-0.1.0.dist-info/RECORD
