Metadata-Version: 2.4
Name: mmplayer-mcp-server
Version: 0.1.0
Summary: Add your description here
Requires-Python: >=3.13
License-File: LICENSE
Requires-Dist: mcp[cli]>=1.4.1
Requires-Dist: pygame>=2.6.1
Requires-Dist: requests>=2.32.3
Dynamic: license-file
